{
  "basics": {
    "name": "Alfred Renn",
    "label": "Software Engineer",
    "image": "",
    "email": "alfredirenn@gmail.com",
    "phone": "+447475 133 651",
    "url": "http://alifeee.co.uk",
    "location": {
      "city": "Birmingham",
      "countryCode": "GB",
      "region": "West Midlands"
    },
    "profiles": [
      {
        "network": "LinkedIn",
        "username": "alfredrenn",
        "url": "https://www.linkedin.com/in/alfredrenn"
      },
      {
        "network": "GitHub",
        "username": "alifeee",
        "url": "https://github.com/alifeee"
      }
    ]
  },
  "work": [
    {
      "name": "ByteSnap Design",
      "position": "Software Engineer",
      "url": "https://www.bytesnap.com/",
      "startDate": "2022-08-22",
      "endDate": "2023-03-03",
      "summary": "",
      "highlights": []
    }
  ],
  "education": [
    {
      "institution": "Durham University",
      "url": "https://www.durham.ac.uk/",
      "area": "Physics",
      "studyType": "MPhys",
      "startDate": "2018-09-01",
      "endDate": "2022-07-06",
      "score": "1st (77%)",
      "courses": [
        "Masters Project",
        "Atoms, Lasers and Qubits",
        "Advanced Theoretical Physics",
        "Advanced Astrophysics",
        "Advanced Laboratory"
      ]
    },
    {
      "institution": "Cottingham High School and Sixth Form College",
      "url": "https://www.cottinghamhigh.net/",
      "studyType": "A Level",
      "startDate": "2016-09-01",
      "endDate": "2018-07-06",
      "score": "A*AA",
      "courses": [
        "A* Physics",
        "A* Mathematics",
        "A* Further Mathematics"
      ]
    },
    {
      "institution": "Cottingham High School and Sixth Form College",
      "url": "https://www.cottinghamhigh.net/",
      "studyType": "GCSE",
      "startDate": "2011-09-01",
      "endDate": "2016-07-06",
      "score": "6A*, 4A, 2D*",
      "courses": [
        "A* Mathematics",
        "A English",
        "+ 5A*, 3A, 2D*"
      ]
    }
  ],
  "volunteer": [
    {
      "organization": "British Heart Foundation",
      "position": "Electrical Testing Volunteer",
      "url": "https://www.bhf.org.uk/",
      "startDate": "2023-03-23",
      "summary": "Testing electrical equipment for the British Heart Foundation."
    }
  ],
  "awards": [
    {
      "title": "Florence Nightingale Award for Graphical Excellence",
      "date": "2019-07-03",
      "awarder": "Durham University",
      "summary": "Awarded for the optimal presentation of quantitative data to illustrate a Helmholtz coil. Used Python for graphing."
    },
    {
      "title": "Durham Award for Academic Excellence",
      "date": "2019-07-03",
      "awarder": "Durham University",
      "summary": "Awarded for achieving over 80% in first year of university."
    }
  ],
  "skills": [
    {
      "name": "Data Analysis",
      "level": "",
      "keywords": [
        "Python",
        "Statistics"
      ]
    },
    {
      "name": "Web Development",
      "level": "",
      "keywords": [
        "HTML",
        "CSS",
        "JavaScript",
        "Vue"
      ]
    }
  ],
  "interests": [
    {
      "name": "Board games",
      "keywords": [
        "Founding president of Board Gaming Society at Sixth Form"
      ]
    },
    {
      "name": "Electronics",
      "keywords": [
        "Arduino (microcontroller and circuit board building)",
        "PC building"
      ]
    },
    {
      "name": "National Citizenship Service",
      "keywords": [
        "Outdoor activities as a team including orienteering",
        "Organisation of charity fundraiser and litter pick as a group of young people"
      ]
    }
  ],
  "languages": [
    {
      "language": "English",
      "fluency": "Native speaker"
    }
  ],
  "meta": {
    "theme": "jsonresume-theme-even"
  }
}